ngram.py
ngram-4.0.3.data/scripts/csvjoin.py
ngram-4.0.3.dist-info/COPYING
ngram-4.0.3.dist-info/COPYING.LESSER
ngram-4.0.3.dist-info/METADATA
ngram-4.0.3.dist-info/WHEEL
ngram-4.0.3.dist-info/top_level.txt
ngram-4.0.3.dist-info/RECORD
