Metadata-Version: 2.1
Name: ngram
Version: 4.0.3
Summary: A `set` subclass providing fuzzy search based on N-grams.
Home-page: https://github.com/gpoulter/python-ngram
Author: Graham Poulter, Michel Albert
Maintainer: Graham Poulter
License: LGPL3
Download-URL: http://pypi.python.org/pypi/ngram
Project-URL: Documentation, https://python-ngram.readthedocs.io/en/latest/
Keywords: ngram set string text similarity
Platform: any
Classifier: Development Status :: 5 - Production/Stable
Classifier: Intended Audience :: Developers
Classifier: License :: OSI Approved :: GNU Lesser General Public License v3 or later (LGPLv3+)
Classifier: License :: OSI Approved :: GNU Lesser General Public License v3 (LGPLv3)
Classifier: License :: OSI Approved :: GNU Library or Lesser General Public License (LGPL)
Classifier: Natural Language :: English
Classifier: Topic :: Text Processing
Classifier: Topic :: Text Processing :: Indexing
Classifier: Topic :: Text Processing :: Linguistic
Classifier: Operating System :: OS Independent
Classifier: Programming Language :: Python
Classifier: Programming Language :: Python :: 3
Requires-Python: >=3.0
License-File: COPYING
License-File: COPYING.LESSER
